{
  "উরয": {
    "description": "savoury suffix",
    "remaining_count": 0,
    "items": []
  },
  "ফফস": {
    "description": "puffs",
    "remaining_count": 0,
    "items": []
  },
  "রিদগে": {
    "description": "porridge",
    "remaining_count": 0,
    "items": []
  },
  "গউরদ": {
    "description": "gourd",
    "remaining_count": 0,
    "items": []
  },
  "মিলক": {
    "description": "milkshake",
    "remaining_count": 0,
    "items": []
  },
  "তোমাত": {
    "description": "tomatoes",
    "remaining_count": 0,
    "items": []
  },
  "পোতাত": {
    "description": "potatoes",
    "remaining_count": 0,
    "items": []
  },
  "পরেস": {
    "description": "preserves",
    "remaining_count": 0,
    "items": []
  },
  "করাক": {
    "description": "cracked",
    "remaining_count": 0,
    "items": []
  },
  "রোাস": {
    "description": "roast",
    "remaining_count": 0,
    "items": []
  },
  "মআইজ": {
    "description": "maize",
    "remaining_count": 0,
    "items": []
  },
  "থিকক": {
    "description": "thickened",
    "remaining_count": 0,
    "items": []
  },
  "বাসকেত": {
    "description": "basket",
    "remaining_count": 0,
    "items": []
  },
  "পাসতে": {
    "description": "paste",
    "remaining_count": 0,
    "items": []
  },
  "হোরনস": {
    "description": "horns",
    "remaining_count": 0,
    "items": []
  },
  "গরউনদ": {
    "description": "groundnut",
    "remaining_count": 0,
    "items": []
  },
  "কেললি": {
    "description": "vermicelli",
    "remaining_count": 0,
    "items": []
  },
  "উইথ": {
    "description": "with",
    "remaining_count": 2,
    "items": [
      {
        "id": 524,
        "en": "Mayonnaise without eggs",
        "bn": "মেয়োনিজ উইথআউট এগস"
      },
      {
        "id": 663,
        "en": "Vanilla ice cream without egg",
        "bn": "ভানিললা আইসক্রিম উইথআউট ডিম"
      }
    ]
  }
}